drf_tweaks/__init__.py
drf_tweaks/autodoc.py
drf_tweaks/autofilter.py
drf_tweaks/mixins.py
drf_tweaks/optimizator.py
drf_tweaks/pagination.py
drf_tweaks/serializers.py
drf_tweaks/versioning.py
drf_tweaks/__pycache__/__init__.cpython-36.pyc
drf_tweaks/__pycache__/autodoc.cpython-36.pyc
drf_tweaks/__pycache__/autofilter.cpython-36.pyc
drf_tweaks/__pycache__/mixins.cpython-36.pyc
drf_tweaks/__pycache__/optimizator.cpython-36.pyc
drf_tweaks/__pycache__/pagination.cpython-36.pyc
drf_tweaks/__pycache__/serializers.cpython-36.pyc
drf_tweaks/__pycache__/versioning.cpython-36.pyc
drf_tweaks/test_utils/__init__.py
drf_tweaks/test_utils/lock_limiter.py
drf_tweaks/test_utils/query_counter.py
drf_tweaks/test_utils/__pycache__/__init__.cpython-36.pyc
drf_tweaks/test_utils/__pycache__/lock_limiter.cpython-36.pyc
drf_tweaks/test_utils/__pycache__/query_counter.cpython-36.pyc
drf_tweaks-0.9.2.dist-info/LICENSE
drf_tweaks-0.9.2.dist-info/METADATA
drf_tweaks-0.9.2.dist-info/WHEEL
drf_tweaks-0.9.2.dist-info/top_level.txt
drf_tweaks-0.9.2.dist-info/RECORD
