Metadata-Version: 2.1
Name: drf-tweaks
Version: 0.9.2
Summary: Set of tweaks for Django Rest Framework
Home-page: https://github.com/ArabellaTech/drf_tweaks
Author: Pawel Krzyzaniak
Author-email: pawelk@arabel.la
License: MIT
Platform: UNKNOWN
Classifier: Development Status :: 4 - Beta
Classifier: Environment :: Web Environment
Classifier: Framework :: Django
Classifier: Intended Audience :: Developers
Classifier: Operating System :: OS Independent
Classifier: Programming Language :: Python
Classifier: Programming Language :: Python :: 3.6
Classifier: Topic :: Internet :: WWW/HTTP
Requires-Dist: six (>=1.10)
Requires-Dist: djangorestframework (>=3.7.0)
Requires-Dist: django-rest-swagger (<2.0.0,>0.3.9)
Requires-Dist: django-filter (>=1.1.0)
